{
  "id": "청고종실록 건륭05년09월29일",
  "jongwon": "etc",
  "title": "",
  "date": "乾隆05年09月29日",
  "transcribed": "",
  "position": "",
  "author": "",
  "summary": "",
  "translated": "",
  "tags": [
    "봉금"
  ],
  "filename": "--------05-09-29-.json",
  "original": "○大學士等議覆。奉天府府尹吳應枚奏、前經兵部侍郎舒赫德奏准、奉天未入籍民人。給限半年。勒令回籍一條。實難辦理。蓋此等民人。寄居年久。遷徙艱難。請將情願入籍者。准取保入籍。其商賈工匠人等。原不侵占旗人地畝。應令地方官就近給印票。使之各自謀生等語。查奉天地方。必須力為清理。方於旗人生計有益。寄居民人。未便聽其入籍。應寬其限期。從緩妥辦。至商賈工匠。應如所請。令地方官給票安業。再該府尹奏稱、旗人地畝。不許全雇民人耕種取租。必須三時力作。相率務農等語。亦應如所請。令該管大臣。立法勸懲。如有不事耕種者。照例將該管官議處。其現在當差者。雇覓民人耕種。仍聽其便。得旨。情願入籍之民。准令取保入籍之處。著照該府尹所請行。其不願入籍者。定限十年。令其陸續回籍。餘依議。",
  "translation": "",
  "updatedAt": "2026-05-03T11:27:34.071Z"
}